LICENSE.txt
MANIFEST.in
README.rst
release_history.rst
requirements.txt
setup.py
crosys/__init__.py
crosys/zzz_manual_install.py
crosys.egg-info/PKG-INFO
crosys.egg-info/SOURCES.txt
crosys.egg-info/dependency_links.txt
crosys.egg-info/top_level.txt
crosys/__pycache__/__init__.cpython-33.pyc